snowflake_stage_exporter/__init__.py
snowflake_stage_exporter/scrapy_pipeline.py
snowflake_stage_exporter/utils.py
tests/__init__.py
tests/record_sql.py
tests/test_exporter.py
tests/test_utils.py
ssb_scrapy_snowflake_stage_exporter-0.0.1.dist-info/METADATA
ssb_scrapy_snowflake_stage_exporter-0.0.1.dist-info/WHEEL
ssb_scrapy_snowflake_stage_exporter-0.0.1.dist-info/top_level.txt
ssb_scrapy_snowflake_stage_exporter-0.0.1.dist-info/RECORD
